<?xml version="1.0" encoding="utf-8"?>
<openerp>
<data noupdate="1">
    <record id="credit_control_policy_multi_company_rule" model="ir.rule">
        <field name="name">Credit Control Policy multi-company</field>
        <field ref="model_credit_control_policy" name="model_id"/>
        <field eval="True" name="global"/>
        <field name="domain_force">['|',('company_id','=',False),('company_id','child_of',[user.company_id.id])]</field>
    </record>

    <record id="credit_control_line_multi_company_rule" model="ir.rule">
        <field name="name">Credit Control Line multi-company</field>
        <field ref="model_credit_control_line" name="model_id"/>
        <field eval="True" name="global"/>
        <field name="domain_force">['|',('company_id','=',False),('company_id','child_of',[user.company_id.id])]</field>
    </record>
</data>
</openerp>
